cnsyn/__init__.py
cnsyn/__main__.py
cnsyn/simwords.py
cnsyn/utils_index.py
cnsyn/chinese_dictionary/sim_words.txt
cnsyn/query/MAIN_WRITELOCK
cnsyn/query/MAIN_ue7k3fkhantq7m50.seg
cnsyn/query/_MAIN_1.toc
cnsyn/query/words_tree_mini.m
cnsyn-1.2.0.dist-info/LICENSE
cnsyn-1.2.0.dist-info/METADATA
cnsyn-1.2.0.dist-info/WHEEL
cnsyn-1.2.0.dist-info/top_level.txt
cnsyn-1.2.0.dist-info/RECORD
