Metadata-Version: 2.1
Name: cnsyn
Version: 1.2.0
Summary: Query tools for Chinese Synonyms
Home-page: https://github.com/shangfr/Chinese-Synonyms
Author: ShangFR
Author-email: shangfr@foxmail.com
Keywords: NLP,simwords,Chinese Synonyms
Classifier: Programming Language :: Python :: 3
Classifier: License :: OSI Approved :: Apache Software License
Classifier: Operating System :: OS Independent
License-File: LICENSE
Requires-Dist: Whoosh (>2.0)
Requires-Dist: scikit-learn (>1.0)
